asciianim.py
asciigraphics.py
asciigraphics-0.1.1.dist-info/LICENSE.txt
asciigraphics-0.1.1.dist-info/METADATA
asciigraphics-0.1.1.dist-info/WHEEL
asciigraphics-0.1.1.dist-info/top_level.txt
asciigraphics-0.1.1.dist-info/RECORD
