Metadata-Version: 2.1
Name: asciigraphics
Version: 0.1.1
Summary: Do Pixel Graphics with ascii charecters
Home-page: https://github.com/beaterblank/ascii-graphics
Author: G.Mohan teja
Author-email: mohanteja.g2019@vitstudent.ac.in
License: UNKNOWN
Platform: UNKNOWN
Classifier: License :: OSI Approved :: GNU General Public License v2 or later (GPLv2+)
Classifier: Operating System :: Microsoft :: Windows :: Windows 10 
Classifier: Programming Language :: Python :: 3.9
Requires-Dist: cursor
Requires-Dist: pyautogui
Requires-Dist: numpy
Requires-Dist: dataclasses
Provides-Extra: dev
Requires-Dist: pytest (>=3.7) ; extra == 'dev'
